pr_telegram_bot/__init__.py
pr_telegram_bot/client.py
pr_telegram_bot/db_service.py
pr_telegram_bot/filters.py
pr_telegram_bot/main.py
pr_telegram_bot/models.py
pr_telegram_bot/py.typed
pr_telegram_bot/state.py
pr_telegram_bot/utils.py
pr_telegram_bot-0.1.3.dist-info/WHEEL
pr_telegram_bot-0.1.3.dist-info/METADATA
pr_telegram_bot-0.1.3.dist-info/RECORD
