Metadata-Version: 2.3
Name: pr-telegram-bot
Version: 0.1.3
Summary: My custom Telegram bot for personal use based on State arhitecture.
Author: Petro Romaniuk
Author-email: Petro Romaniuk <pr@email.com>
Requires-Dist: aiohttp>=3.13.2
Requires-Dist: pydantic>=2.12.4
Requires-Dist: pymongo>=4.15.4
Requires-Dist: pytelegrambotapi>=4.29.1
Requires-Python: >=3.13
